nanonets/__init__.py
nanonets/classification.py
nanonets/model.py
nanonets/multilabel_classification.py
nanonets/object_detection.py
nanonets/ocr.py
nanonets/utils.py
nanonets-2.0.5.dist-info/METADATA
nanonets-2.0.5.dist-info/WHEEL
nanonets-2.0.5.dist-info/top_level.txt
nanonets-2.0.5.dist-info/RECORD
