Metadata-Version: 2.1
Name: nanonets
Version: 2.0.5
Summary: The Nanonets API
Home-page: https://nanonets.com
Author-email: support@nanonets.com
License: UNKNOWN
Platform: UNKNOWN
Requires-Dist: requests (==2.22.0)
Requires-Dist: setuptools (==41.0.1)
Requires-Dist: tqdm (==4.36.1)
Requires-Dist: xmljson (==0.2.0)
